photo_quality_analyzer_core/__init__.py
photo_quality_analyzer_core/analyzer.py
photo_quality_analyzer_core/context_helpers.py
photo_quality_analyzer_core-0.4.0.dist-info/licenses/LICENSE
photo_quality_analyzer_core-0.4.0.dist-info/METADATA
photo_quality_analyzer_core-0.4.0.dist-info/WHEEL
photo_quality_analyzer_core-0.4.0.dist-info/top_level.txt
photo_quality_analyzer_core-0.4.0.dist-info/RECORD
