Metadata-Version: 2.4
Name: photo_quality_analyzer_core
Version: 0.4.0
Summary: The Python SDK for Local Computer Vision & Signal Processing
Author: Abhishek Prasad
Classifier: Development Status :: 4 - Beta
Classifier: Intended Audience :: Developers
Classifier: Intended Audience :: Science/Research
Classifier: Topic :: Multimedia :: Graphics :: Capture :: Digital Camera
Classifier: Topic :: Scientific/Engineering :: Image Processing
Classifier: License :: OSI Approved :: MIT License
Classifier: Programming Language :: Python :: 3
Requires-Python: >=3.10
License-File: LICENSE
Requires-Dist: opencv-python>=4.10.0
Requires-Dist: numpy>=1.26.0
Requires-Dist: ultralytics>=8.3.0
Requires-Dist: tqdm>=4.66.0
Requires-Dist: exifread>=3.0.0
Requires-Dist: scipy>=1.14.0
Requires-Dist: rawpy>=0.23.0
Provides-Extra: test
Requires-Dist: unittest; extra == "test"
Dynamic: license-file
